div/__init__.py
div/cli.py
div/lib.py
div/py.typed
python_starter_package-1.0.0.dist-info/LICENSE.txt
python_starter_package-1.0.0.dist-info/METADATA
python_starter_package-1.0.0.dist-info/WHEEL
python_starter_package-1.0.0.dist-info/entry_points.txt
python_starter_package-1.0.0.dist-info/top_level.txt
python_starter_package-1.0.0.dist-info/RECORD
